algorithms_OhGreat/DART.py
algorithms_OhGreat/FBP.py
algorithms_OhGreat/SART.py
algorithms_OhGreat/SIRT.py
algorithms_OhGreat/__init__.py
phantoms_OhGreat/__init__.py
phantoms_OhGreat/creator.py
projections_OhGreat/__init__.py
projections_OhGreat/project.py
utils_OhGreat/__init__.py
utils_OhGreat/utils.py
DART_OhGreat-0.0.5.dist-info/LICENCE
DART_OhGreat-0.0.5.dist-info/METADATA
DART_OhGreat-0.0.5.dist-info/WHEEL
DART_OhGreat-0.0.5.dist-info/top_level.txt
DART_OhGreat-0.0.5.dist-info/RECORD
