Metadata-Version: 2.1
Name: DART-OhGreat
Version: 0.0.5
Summary: A python implementation of the DART algorithm.
Author-email: Dimitrios Ieronymakis <ieronymakis.dim@protonmail.com>
Project-URL: Homepage, https://github.com/OhGreat/DART_python
Project-URL: Bug Tracker, https://github.com/OhGreat/DART_python/issues
Classifier: Programming Language :: Python :: 3
Classifier: License :: OSI Approved :: MIT License
Classifier: Operating System :: OS Independent
Requires-Python: >=3.8
License-File: LICENCE
Requires-Dist: numpy (>=1.22.0)
Requires-Dist: matplotlib (>=3.5.0)
Requires-Dist: Pillow (>=9.1.1)
Requires-Dist: scipy (>=1.8.0)
